Workbook

Sheet 1. Suba Himalaya
A1: SUBA HIMALAYA PROJECT — SALES PROJECTION 2027–2031
A2: Base model (24 months) re-distributed over 5 years · 92 apt + 110 parking + 18 terraces · Figures in USD · FX ref. $4,200 COP/USD
A4: 1. ASSUMPTIONS — SALES DISTRIBUTION AND TAX RATES (editable · blue text)
A5: Concept | B5: Base 24m (USD) | C5: 2027 | D5: 2028 | E5: 2029 | F5: 2030 | G5: 2031 | H5: TOTAL
A6: Sales distribution (% per year) | B6: — | C6: 0.15 | D6: 0.25 | E6: 0.3 | F6: 0.2 | G6: 0.1 | H6: =SUM(C6:G6) -> 1
A7: Income Tax (on pre-tax profit) | B7: 0.35
A8: Withholding Tax (on sales) | B8: 0.01
A9: ReteICA / ICA Withholding (on sales) | B9: 0.0033
A10: Industry & Commerce Tax – ICA (on sales) | B10: 0.0033
A11: 2. SALES REVENUE (USD)
A12: Concept | B12: Base 24m (USD) | C12: 2027 | D12: 2028 | E12: 2029 | F12: 2030 | G12: 2031 | H12: TOTAL
A13: Apartment sales (92 units) | B13: 52189629 | C13: =$B13*C$6 -> 7828444.3 | D13: =$B13*D$6 -> 13047407 | E13: =$B13*E$6 -> 15656889 | F13: =$B13*F$6 -> 10437926 | G13: =$B13*G$6 -> 5218962.9 | H13: =SUM(C13:G13) -> 52189629
A14: Parking with storage (110 units) | B14: 1571428.6 | C14: =$B14*C$6 -> 235714.29 | D14: =$B14*D$6 -> 392857.14 | E14: =$B14*E$6 -> 471428.57 | F14: =$B14*F$6 -> 314285.71 | G14: =$B14*G$6 -> 157142.86 | H14: =SUM(C14:G14) -> 1571428.6
A15: Terrace sales (18 units) | B15: 17142.857 | C15: =$B15*C$6 -> 2571.4286 | D15: =$B15*D$6 -> 4285.7143 | E15: =$B15*E$6 -> 5142.8571 | F15: =$B15*F$6 -> 3428.5714 | G15: =$B15*G$6 -> 1714.2857 | H15: =SUM(C15:G15) -> 17142.857
A16: TOTAL SALES REVENUE | B16: =SUM(B13:B15) -> 53778200 | C16: =SUM(C13:C15) -> 8066730 | D16: =SUM(D13:D15) -> 13444550 | E16: =SUM(E13:E15) -> 16133460 | F16: =SUM(F13:F15) -> 10755640 | G16: =SUM(G13:G15) -> 5377820 | H16: =SUM(H13:H15) -> 53778200
A18: 3. PROJECT COSTS (USD)
A19: Concept | B19: Base 24m (USD) | C19: 2027 | D19: 2028 | E19: 2029 | F19: 2030 | G19: 2031 | H19: TOTAL
A20: Direct construction cost | B20: 8071310.1 | C20: =$B20*C$6 -> 1210696.5 | D20: =$B20*D$6 -> 2017827.5 | E20: =$B20*E$6 -> 2421393 | F20: =$B20*F$6 -> 1614262 | G20: =$B20*G$6 -> 807131.01 | H20: =SUM(C20:G20) -> 8071310.1
A21: Indirect construction cost | B21: 1311969.9 | C21: =$B21*C$6 -> 196795.49 | D21: =$B21*D$6 -> 327992.48 | E21: =$B21*E$6 -> 393590.98 | F21: =$B21*F$6 -> 262393.99 | G21: =$B21*G$6 -> 131196.99 | H21: =SUM(C21:G21) -> 1311969.9
A22: Fiduciary and administrative expenses | B22: 1006610.5 | C22: =$B22*C$6 -> 150991.57 | D22: =$B22*D$6 -> 251652.62 | E22: =$B22*E$6 -> 301983.15 | F22: =$B22*F$6 -> 201322.1 | G22: =$B22*G$6 -> 100661.05 | H22: =SUM(C22:G22) -> 1006610.5
A23: Financial costs (loan + 4×1000 FTT) | B23: 0 | C23: =$B23*C$6 -> 0 | D23: =$B23*D$6 -> 0 | E23: =$B23*E$6 -> 0 | F23: =$B23*F$6 -> 0 | G23: =$B23*G$6 -> 0 | H23: =SUM(C23:G23) -> 0
A24: Fees, sales and marketing | B24: 5377820 | C24: =$B24*C$6 -> 806673 | D24: =$B24*D$6 -> 1344455 | E24: =$B24*E$6 -> 1613346 | F24: =$B24*F$6 -> 1075564 | G24: =$B24*G$6 -> 537782 | H24: =SUM(C24:G24) -> 5377820
A25: Land acquisition | B25: 13444550 | C25: =$B25*C$6 -> 2016682.5 | D25: =$B25*D$6 -> 3361137.5 | E25: =$B25*E$6 -> 4033365 | F25: =$B25*F$6 -> 2688910 | G25: =$B25*G$6 -> 1344455 | H25: =SUM(C25:G25) -> 13444550
A26: TOTAL PROJECT COSTS | B26: =SUM(B20:B25) -> 29212261 | C26: =SUM(C20:C25) -> 4381839.1 | D26: =SUM(D20:D25) -> 7303065.1 | E26: =SUM(E20:E25) -> 8763678.2 | F26: =SUM(F20:F25) -> 5842452.1 | G26: =SUM(G20:G25) -> 2921226.1 | H26: =SUM(H20:H25) -> 29212261
A28: 4. PRE-TAX PROFIT (USD)
A29: Pre-tax profit | B29: =B16-B26 -> 24565939 | C29: =C16-C26 -> 3684890.9 | D29: =D16-D26 -> 6141484.9 | E29: =E16-E26 -> 7369781.8 | F29: =F16-F26 -> 4913187.9 | G29: =G16-G26 -> 2456593.9 | H29: =SUM(C29:G29) -> 24565939
A31: 5. TAX BURDEN (USD)
A32: Concept | B32: Base 24m (USD) | C32: 2027 | D32: 2028 | E32: 2029 | F32: 2030 | G32: 2031 | H32: TOTAL
A33: Income Tax (35% on profit) | B33: =$B$7*B29 -> 8598078.8 | C33: =$B$7*C29 -> 1289711.8 | D33: =$B$7*D29 -> 2149519.7 | E33: =$B$7*E29 -> 2579423.6 | F33: =$B$7*F29 -> 1719615.8 | G33: =$B$7*G29 -> 859807.88 | H33: =SUM(C33:G33) -> 8598078.8
A34: Withholding Tax (1% on sales) | B34: =$B$8*B16 -> 537782 | C34: =$B$8*C16 -> 80667.3 | D34: =$B$8*D16 -> 134445.5 | E34: =$B$8*E16 -> 161334.6 | F34: =$B$8*F16 -> 107556.4 | G34: =$B$8*G16 -> 53778.2 | H34: =SUM(C34:G34) -> 537782
A35: ReteICA / ICA Withholding (0.33% on sales) | B35: =$B$9*B16 -> 177468.06 | C35: =$B$9*C16 -> 26620.209 | D35: =$B$9*D16 -> 44367.015 | E35: =$B$9*E16 -> 53240.418 | F35: =$B$9*F16 -> 35493.612 | G35: =$B$9*G16 -> 17746.806 | H35: =SUM(C35:G35) -> 177468.06
A36: Industry & Commerce Tax – ICA (0.33% on sales) | B36: =$B$10*B16 -> 177468.06 | C36: =$B$10*C16 -> 26620.209 | D36: =$B$10*D16 -> 44367.015 | E36: =$B$10*E16 -> 53240.418 | F36: =$B$10*F16 -> 35493.612 | G36: =$B$10*G16 -> 17746.806 | H36: =SUM(C36:G36) -> 177468.06
A37: TOTAL TAX BURDEN | B37: =SUM(B33:B36) -> 9490796.9 | C37: =SUM(C33:C36) -> 1423619.5 | D37: =SUM(D33:D36) -> 2372699.2 | E37: =SUM(E33:E36) -> 2847239.1 | F37: =SUM(F33:F36) -> 1898159.4 | G37: =SUM(G33:G36) -> 949079.69 | H37: =SUM(H33:H36) -> 9490796.9
A39: 6. NET CASH FLOW / NET PROFIT (USD)
A40: Concept | B40: Base 24m (USD) | C40: 2027 | D40: 2028 | E40: 2029 | F40: 2030 | G40: 2031 | H40: TOTAL
A41: Annual net profit (net cash flow) | B41: =B29-B37 -> 15075143 | C41: =C29-C37 -> 2261271.4 | D41: =D29-D37 -> 3768785.6 | E41: =E29-E37 -> 4522542.8 | F41: =F29-F37 -> 3015028.5 | G41: =G29-G37 -> 1507514.3 | H41: =SUM(C41:G41) -> 15075143
A42: Cumulative net cash flow | B42: — | C42: =C41 -> 2261271.4 | D42: =C42+D41 -> 6030057 | E42: =D42+E41 -> 10552600 | F42: =E42+F41 -> 13567628 | G42: =F42+G41 -> 15075143 | H42: =G42 -> 15075143
A43: Net margin (net profit / sales) | B43: — | C43: =IFERROR(C41/C16,0) -> 0.2803207 | D43: =IFERROR(D41/D16,0) -> 0.2803207 | E43: =IFERROR(E41/E16,0) -> 0.2803207 | F43: =IFERROR(F41/F16,0) -> 0.2803207 | G43: =IFERROR(G41/G16,0) -> 0.2803207 | H43: =IFERROR(H41/H16,0) -> 0.2803207
A44: Annual ROI (net profit / costs) | B44: — | C44: =IFERROR(C41/C26,0) -> 0.51605532 | D44: =IFERROR(D41/D26,0) -> 0.51605532 | E44: =IFERROR(E41/E26,0) -> 0.51605532 | F44: =IFERROR(F41/F26,0) -> 0.51605532 | G44: =IFERROR(G41/G26,0) -> 0.51605532 | H44: =IFERROR(H41/H26,0) -> 0.51605532
A46: Note: sales are distributed using the editable curve (row 6). Costs and tax burden are pro-rated over the same curve, so annual totals reconcile exactly with the 24-month base model. FX applied: 4,200 COP/USD.

Sheet 2. Santa Barbara
A1: SANTA BARBARA PROJECT — SALES PROJECTION 2027–2028
A2: 118th Street # 22A, Bogotá · 25 apartments + 3 terraces · Figures in USD · FX ref. $4,200 COP/USD
A4: 1. ASSUMPTIONS — SALES DISTRIBUTION AND TAX RATES (editable · blue text)
A5: Concept | B5: Base 24m (USD) | C5: 2027 | D5: 2028 | E5: TOTAL
A6: Sales distribution (% per year) | B6: — | C6: 0.45 | D6: 0.55 | E6: =SUM(C6:D6) -> 1
A7: Income Tax (on pre-tax profit) | B7: 0.35
A8: Withholding Tax (on sales) | B8: 0.01
A9: ReteICA / ICA Withholding (on sales) | B9: 0.0033
A10: Industry & Commerce Tax – ICA (on sales) | B10: 0.0033
A11: 2. SALES REVENUE (USD)
A12: Concept | B12: Base 24m (USD) | C12: 2027 | D12: 2028 | E12: TOTAL
A13: Apartment sales (25 units) | B13: 7136232.1 | C13: =$B13*C$6 -> 3211304.5 | D13: =$B13*D$6 -> 3924927.7 | E13: =SUM(C13:D13) -> 7136232.1
A14: Terrace sales (3 units) | B14: 71809.643 | C14: =$B14*C$6 -> 32314.339 | D14: =$B14*D$6 -> 39495.304 | E14: =SUM(C14:D14) -> 71809.643
A15: Parking / storage (37 units) | B15: 0 | C15: =$B15*C$6 -> 0 | D15: =$B15*D$6 -> 0 | E15: =SUM(C15:D15) -> 0
A16: TOTAL SALES REVENUE | B16: =SUM(B13:B15) -> 7208041.8 | C16: =SUM(C13:C15) -> 3243618.8 | D16: =SUM(D13:D15) -> 3964423 | E16: =SUM(E13:E15) -> 7208041.8
A18: 3. PROJECT COSTS (USD)
A19: Concept | B19: Base 24m (USD) | C19: 2027 | D19: 2028 | E19: TOTAL
A20: CAPEX – Land acquisition | B20: 1614282.8 | C20: =$B20*C$6 -> 726427.24 | D20: =$B20*D$6 -> 887855.52 | E20: =SUM(C20:D20) -> 1614282.8
A21: CAPEX – Direct construction (structure + finishes) | B21: 2923996.4 | C21: =$B21*C$6 -> 1315798.4 | D21: =$B21*D$6 -> 1608198 | E21: =SUM(C21:D21) -> 2923996.4
A22: OPEX – Indirect construction costs | B22: 438857.79 | C22: =$B22*C$6 -> 197486.01 | D22: =$B22*D$6 -> 241371.78 | E22: =SUM(C22:D22) -> 438857.79
A23: OPEX – Fiduciary and administrative expenses | B23: 305620.97 | C23: =$B23*C$6 -> 137529.44 | D23: =$B23*D$6 -> 168091.53 | E23: =SUM(C23:D23) -> 305620.97
A24: OPEX – Financial costs + 4×1000 FTT | B24: 256188.22 | C24: =$B24*C$6 -> 115284.7 | D24: =$B24*D$6 -> 140903.52 | E24: =SUM(C24:D24) -> 256188.22
A25: OPEX – Fees, sales and marketing | B25: 648723.76 | C25: =$B25*C$6 -> 291925.69 | D25: =$B25*D$6 -> 356798.07 | E25: =SUM(C25:D25) -> 648723.76
A26: TOTAL PROJECT COSTS | B26: =SUM(B20:B25) -> 6187669.9 | C26: =SUM(C20:C25) -> 2784451.5 | D26: =SUM(D20:D25) -> 3403218.4 | E26: =SUM(E20:E25) -> 6187669.9
A28: 4. PRE-TAX PROFIT (USD)
A29: Pre-tax profit | B29: =B16-B26 -> 1020371.9 | C29: =C16-C26 -> 459167.35 | D29: =D16-D26 -> 561204.54 | E29: =SUM(C29:D29) -> 1020371.9
A31: 5. TAX BURDEN (USD)
A32: Concept | B32: Base 24m (USD) | C32: 2027 | D32: 2028 | E32: TOTAL
A33: Income Tax (35% on profit) | B33: =$B$7*B29 -> 357130.16 | C33: =$B$7*C29 -> 160708.57 | D33: =$B$7*D29 -> 196421.59 | E33: =SUM(C33:D33) -> 357130.16
A34: Withholding Tax (1% on sales) | B34: =$B$8*B16 -> 72080.418 | C34: =$B$8*C16 -> 32436.188 | D34: =$B$8*D16 -> 39644.23 | E34: =SUM(C34:D34) -> 72080.418
A35: ReteICA / ICA Withholding (0.33% on sales) | B35: =$B$9*B16 -> 23786.538 | C35: =$B$9*C16 -> 10703.942 | D35: =$B$9*D16 -> 13082.596 | E35: =SUM(C35:D35) -> 23786.538
A36: Industry & Commerce Tax – ICA (0.33% on sales) | B36: =$B$10*B16 -> 23786.538 | C36: =$B$10*C16 -> 10703.942 | D36: =$B$10*D16 -> 13082.596 | E36: =SUM(C36:D36) -> 23786.538
A37: TOTAL TAX BURDEN | B37: =SUM(B33:B36) -> 476783.66 | C37: =SUM(C33:C36) -> 214552.65 | D37: =SUM(D33:D36) -> 262231.01 | E37: =SUM(E33:E36) -> 476783.66
A39: 6. NET CASH FLOW / NET PROFIT (USD)
A40: Concept | B40: Base 24m (USD) | C40: 2027 | D40: 2028 | E40: TOTAL
A41: Annual net profit (net cash flow) | B41: =B29-B37 -> 543588.24 | C41: =C29-C37 -> 244614.71 | D41: =D29-D37 -> 298973.53 | E41: =SUM(C41:D41) -> 543588.24
A42: Cumulative net cash flow | B42: — | C42: =C41 -> 244614.71 | D42: =C42+D41 -> 543588.24 | E42: =D42 -> 543588.24
A43: Net margin (net profit / sales) | B43: — | C43: =IFERROR(C41/C16,0) -> 0.075414135 | D43: =IFERROR(D41/D16,0) -> 0.075414135 | E43: =IFERROR(E41/E16,0) -> 0.075414135
A44: Annual ROI (net profit / costs) | B44: — | C44: =IFERROR(C41/C26,0) -> 0.087850232 | D44: =IFERROR(D41/D26,0) -> 0.087850232 | E44: =IFERROR(E41/E26,0) -> 0.087850232
A46: Note: short-cycle project (24 months) re-distributed over 2 years. The 4×1000 financial transaction tax is included in the project financial costs. Totals reconcile with the base model. FX applied: 4,200 COP/USD.

Sheet 3. Consolidated
A1: CONSOLIDATED & NET PROFIT
A2: Suba Himalaya + Santa Barbara · Gross profit, tax burden and net profit · Figures in USD · June 2026
A4: 1. CONSOLIDATED NET PROFIT (USD)
A5: Concept | B5: Suba Himalaya | C5: Santa Barbara | D5: CONSOLIDATED | E5: Note
A6: Sales revenue | B6: ='1. Suba Himalaya'!H16 -> 53778200 | C6: ='2. Santa Barbara'!E16 -> 7208041.8 | D6: =B6+C6 -> 60986242 | E6: Suba: 92 apt+110 park+18 terr · SB: 25 apt+3 terr
A7: (–) Total project costs | B7: ='1. Suba Himalaya'!H26 -> 29212261 | C7: ='2. Santa Barbara'!E26 -> 6187669.9 | D7: =B7+C7 -> 35399930 | E7: Integrated CAPEX + OPEX
A8: GROSS PROFIT BEFORE TAX | B8: =B6-B7 -> 24565939 | C8: =C6-C7 -> 1020371.9 | D8: =D6-D7 -> 25586311 | E8: Revenue − costs
A9: (–) Project tax burden | B9: ='1. Suba Himalaya'!H37 -> 9490796.9 | C9: ='2. Santa Barbara'!E37 -> 476783.66 | D9: =B9+C9 -> 9967580.6 | E9: Income Tax + Withholding + ReteICA + ICA per project
A10: NET PROJECT PROFIT | B10: =B8-B9 -> 15075143 | C10: =C8-C9 -> 543588.24 | D10: =D8-D9 -> 15618731 | E10: Final net profit per project and consolidated
A11: Net margin / sales | B11: =IFERROR(B10/B6,0) -> 0.2803207 | C11: =IFERROR(C10/C6,0) -> 0.075414135 | D11: =IFERROR(D10/D6,0) -> 0.25610253 | E11: Net profit / revenue
A12: ROI (net profit / costs) | B12: =IFERROR(B10/B7,0) -> 0.51605532 | C12: =IFERROR(C10/C7,0) -> 0.087850232 | D12: =IFERROR(D10/D7,0) -> 0.44120795 | E12: Return on total investment
A14: 2. CONSOLIDATED TAX BURDEN BREAKDOWN (Income Tax · ICA · ReteICA · 4×1000 FTT)
A15: 4×1000 FTT rate (4‰ on movements · editable) | D15: 0.004 | E15: Applied on trust disbursements + collections
A16: Concept | B16: Suba Himalaya | C16: Santa Barbara | D16: CONSOLIDATED | E16: Base / remark
A17: Income Tax (35% on profit) | B17: ='1. Suba Himalaya'!H33 -> 8598078.8 | C17: ='2. Santa Barbara'!E33 -> 357130.16 | D17: =B17+C17 -> 8955209 | E17: Art. 240 ET · 35% 2026
A18: Withholding Tax (1% on sales) | B18: ='1. Suba Himalaya'!H34 -> 537782 | C18: ='2. Santa Barbara'!E34 -> 72080.418 | D18: =B18+C18 -> 609862.42 | E18: Art. 401 ET · creditable advance
A19: ReteICA / ICA Withholding (0.33% on sales) | B19: ='1. Suba Himalaya'!H35 -> 177468.06 | C19: ='2. Santa Barbara'!E35 -> 23786.538 | D19: =B19+C19 -> 201254.6 | E19: Agreement 65/2002 Bogotá · advance
A20: Industry & Commerce Tax – ICA (0.33% on sales) | B20: ='1. Suba Himalaya'!H36 -> 177468.06 | C20: ='2. Santa Barbara'!E36 -> 23786.538 | D20: =B20+C20 -> 201254.6 | E20: Law 14/1983 · activity 4010
A21: 4×1000 FTT (on financial movements) | B21: — | C21: — | D21: =$D$15*(D6+D7) -> 385544.69 | E21: Art. 872 ET · 0.4% on collections + disbursements
A22: TOTAL TAX BURDEN (tax cash view) | B22: =SUM(B17:B20) -> 9490796.9 | C22: =SUM(C17:C20) -> 476783.66 | D22: =SUM(D17:D21) -> 10353125 | E22: Includes advances (Withholding/ReteICA) and FTT
A24: CFO note: the Net Profit in Section 1 is obtained by subtracting from gross profit each project own tax burden (Income Tax + Withholding + ReteICA + ICA). Section 2 is an expanded tax-cash view adding the 4×1000 FTT on the trust movements; withholdings and ReteICA are creditable advances against income tax, not an additional definitive cost.

Sheet 4. Executive Summary
A1: CONSOLIDATED FINANCIAL MODEL — EXECUTIVE SUMMARY
A2: Suba Himalaya Project + Santa Barbara Project · Figures in USD · FX ref. $4,200 COP/USD · June 2026
A4: 1. PROJECT DESCRIPTION
A5: SUBA HIMALAYA: residential development in Bogotá with 92 apartments, 110 parking spaces with storage and 18 terraces, with a sellable area of 21,919 m². Model re-projected over 5 years (2027–2031) under Colombian IFRS (IAS 11 / IFRS 15).
A7: SANTA BARBARA: short-cycle project on 118th Street # 22A (Bogotá), 25 apartments and 3 duplex terraces, built area of 3,739 m². Model re-projected over 2 years (2027–2028) with a CAPEX/OPEX structure and a construction loan.
A10: 2. REVENUE AND RESULTS SUMMARY (USD)
A11: Concept | B11: Suba Himalaya | C11: Santa Barbara | D11: Consolidated
A12: Total projected revenue | B12: ='3. Consolidated'!B6 -> 53778200 | C12: ='3. Consolidated'!C6 -> 7208041.8 | D12: ='3. Consolidated'!D6 -> 60986242
A13: Total project costs | B13: ='3. Consolidated'!B7 -> 29212261 | C13: ='3. Consolidated'!C7 -> 6187669.9 | D13: ='3. Consolidated'!D7 -> 35399930
A14: Gross profit before tax | B14: ='3. Consolidated'!B8 -> 24565939 | C14: ='3. Consolidated'!C8 -> 1020371.9 | D14: ='3. Consolidated'!D8 -> 25586311
A15: Total tax burden | B15: ='3. Consolidated'!B9 -> 9490796.9 | C15: ='3. Consolidated'!C9 -> 476783.66 | D15: ='3. Consolidated'!D9 -> 9967580.6
A16: NET PROFIT | B16: ='3. Consolidated'!B10 -> 15075143 | C16: ='3. Consolidated'!C10 -> 543588.24 | D16: ='3. Consolidated'!D10 -> 15618731
A17: Net margin / sales | B17: ='3. Consolidated'!B11 -> 0.2803207 | C17: ='3. Consolidated'!C11 -> 0.075414135 | D17: ='3. Consolidated'!D11 -> 0.25610253
A18: ROI (net profit / costs) | B18: ='3. Consolidated'!B12 -> 0.51605532 | C18: ='3. Consolidated'!C12 -> 0.087850232 | D18: ='3. Consolidated'!D12 -> 0.44120795
A20: 3. IMPACT OF THE TAX BURDEN ON PROFITABILITY
A21: The consolidated tax burden (Income Tax 35%, Withholding Tax 1%, ReteICA and ICA 0.33%) amounts to ~USD 9.97 million, equivalent to 16.3% of total revenue and 39% of gross profit. Income Tax concentrates most of the burden (~USD 8.96 million). Suba Himalaya bears nearly all of the taxation due to its larger scale and margin, while Santa Barbara —with a 7.5% net margin— is far more sensitive to the tax burden and to the construction loan financial costs. The 4×1000 FTT on the trust movements (~USD 0.39 million) is an additional cash cost, partially deductible (50%, Art. 115 ET).
A26: 4. CONCLUSIONS ON FINANCIAL VIABILITY
A27: The consolidated portfolio is financially viable: it generates projected revenue of ~USD 60.99 million and a consolidated net profit of ~USD 15.62 million, with a 25.6% net margin and a ROI near 44%. Suba Himalaya is the profitability engine (28.0% net margin, 51.6% ROI) and justifies the investment on its own. Santa Barbara, although with a tighter margin (7.5%) and higher exposure to financial costs, adds diversification and short-cycle liquidity (2 years) that helps fund the remainder of the trust. Recommendation: prioritize early pre-sales in Suba to activate the trust, monitor Santa Barbara sensitivity to the loan cost (15.6% EAR), and optimize the deductibility of the FTT. The USD 25 million trust fund covers ~71% of the integrated cost; the balance is financed with pre-sales collections.
A33: Pre-feasibility document · Figures subject to update based on construction progress and tax adjustments · Prepared from the attached consolidated financial model.
