Workbook

Sheet 1. Suba Himalaya
A1: PROYECTO SUBA HIMALAYA — PROYECCIÓN DE VENTAS 2027–2031
A2: Re-distribución del modelo base (24 meses) a 5 años · 92 apt + 110 parq + 18 terrazas · Cifras en COP · TRM ref. $4.200
A4: 1. SUPUESTOS — DISTRIBUCIÓN DE VENTAS Y TARIFAS IMPOSITIVAS (editables · texto azul)
A5: Concepto | B5: Base 24m (COP) | C5: 2027 | D5: 2028 | E5: 2029 | F5: 2030 | G5: 2031 | H5: TOTAL
A6: Distribución de ventas (% por año) | B6: — | C6: 0.15 | D6: 0.25 | E6: 0.3 | F6: 0.2 | G6: 0.1 | H6: =SUM(C6:G6) -> 1
A7: Impuesto de Renta (s/ utilidad antes de imp.) | B7: 0.35
A8: Retención en la Fuente (s/ ventas) | B8: 0.01
A9: ReteICA (s/ ventas) | B9: 0.0033
A10: ICA (s/ ventas) | B10: 0.0033
A11: 2. INGRESOS POR VENTAS (COP)
A12: Concepto | B12: Base 24m (COP) | C12: 2027 | D12: 2028 | E12: 2029 | F12: 2030 | G12: 2031 | H12: TOTAL
A13: Venta de apartamentos (92 unidades) | B13: 219196440000 | C13: =$B13*C$6 -> 32879466000 | D13: =$B13*D$6 -> 54799110000 | E13: =$B13*E$6 -> 65758932000 | F13: =$B13*F$6 -> 43839288000 | G13: =$B13*G$6 -> 21919644000 | H13: =SUM(C13:G13) -> 219196440000
A14: Parqueaderos con depósito (110 unidades) | B14: 6600000000 | C14: =$B14*C$6 -> 990000000 | D14: =$B14*D$6 -> 1650000000 | E14: =$B14*E$6 -> 1980000000 | F14: =$B14*F$6 -> 1320000000 | G14: =$B14*G$6 -> 660000000 | H14: =SUM(C14:G14) -> 6600000000
A15: Venta de terrazas (18 unidades) | B15: 72000000 | C15: =$B15*C$6 -> 10800000 | D15: =$B15*D$6 -> 18000000 | E15: =$B15*E$6 -> 21600000 | F15: =$B15*F$6 -> 14400000 | G15: =$B15*G$6 -> 7200000 | H15: =SUM(C15:G15) -> 72000000
A16: TOTAL INGRESOS POR VENTAS | B16: =SUM(B13:B15) -> 225868440000 | C16: =SUM(C13:C15) -> 33880266000 | D16: =SUM(D13:D15) -> 56467110000 | E16: =SUM(E13:E15) -> 67760532000 | F16: =SUM(F13:F15) -> 45173688000 | G16: =SUM(G13:G15) -> 22586844000 | H16: =SUM(H13:H15) -> 225868440000
A18: 3. COSTOS DEL PROYECTO (COP)
A19: Concepto | B19: Base 24m (COP) | C19: 2027 | D19: 2028 | E19: 2029 | F19: 2030 | G19: 2031 | H19: TOTAL
A20: Costo directo de construcción | B20: 33899502570 | C20: =$B20*C$6 -> 5.0849254e+09 | D20: =$B20*D$6 -> 8.4748756e+09 | E20: =$B20*E$6 -> 10169850771 | F20: =$B20*F$6 -> 6779900514 | G20: =$B20*G$6 -> 3389950257 | H20: =SUM(C20:G20) -> 33899502570
A21: Costo indirecto de construcción | B21: 5510273722 | C21: =$B21*C$6 -> 8.2654106e+08 | D21: =$B21*D$6 -> 1.3775684e+09 | E21: =$B21*E$6 -> 1.6530821e+09 | F21: =$B21*F$6 -> 1.1020547e+09 | G21: =$B21*G$6 -> 5.5102737e+08 | H21: =SUM(C21:G21) -> 5510273722
A22: Gastos fiduciarios y administrativos | B22: 4227764057 | C22: =$B22*C$6 -> 6.3416461e+08 | D22: =$B22*D$6 -> 1.056941e+09 | E22: =$B22*E$6 -> 1.2683292e+09 | F22: =$B22*F$6 -> 8.4555281e+08 | G22: =$B22*G$6 -> 4.2277641e+08 | H22: =SUM(C22:G22) -> 4227764057
A23: Costos financieros (crédito + 4×1000) | B23: 0 | C23: =$B23*C$6 -> 0 | D23: =$B23*D$6 -> 0 | E23: =$B23*E$6 -> 0 | F23: =$B23*F$6 -> 0 | G23: =$B23*G$6 -> 0 | H23: =SUM(C23:G23) -> 0
A24: Honorarios, ventas y publicidad | B24: 22586844000 | C24: =$B24*C$6 -> 3388026600 | D24: =$B24*D$6 -> 5646711000 | E24: =$B24*E$6 -> 6776053200 | F24: =$B24*F$6 -> 4517368800 | G24: =$B24*G$6 -> 2258684400 | H24: =SUM(C24:G24) -> 22586844000
A25: Adquisición de terreno | B25: 56467110000 | C25: =$B25*C$6 -> 8470066500 | D25: =$B25*D$6 -> 14116777500 | E25: =$B25*E$6 -> 16940133000 | F25: =$B25*F$6 -> 11293422000 | G25: =$B25*G$6 -> 5646711000 | H25: =SUM(C25:G25) -> 56467110000
A26: TOTAL COSTOS DEL PROYECTO | B26: =SUM(B20:B25) -> 122691494349 | C26: =SUM(C20:C25) -> 1.8403724e+10 | D26: =SUM(D20:D25) -> 3.0672874e+10 | E26: =SUM(E20:E25) -> 3.6807448e+10 | F26: =SUM(F20:F25) -> 2.4538299e+10 | G26: =SUM(G20:G25) -> 1.2269149e+10 | H26: =SUM(H20:H25) -> 122691494349
A28: 4. UTILIDAD ANTES DE IMPUESTOS (COP)
A29: Utilidad antes de impuestos | B29: =B16-B26 -> 103176945651 | C29: =C16-C26 -> 1.5476542e+10 | D29: =D16-D26 -> 2.5794236e+10 | E29: =E16-E26 -> 3.0953084e+10 | F29: =F16-F26 -> 2.0635389e+10 | G29: =G16-G26 -> 1.0317695e+10 | H29: =SUM(C29:G29) -> 103176945651
A31: 5. CARGA TRIBUTARIA (COP)
A32: Concepto | B32: Base 24m (COP) | C32: 2027 | D32: 2028 | E32: 2029 | F32: 2030 | G32: 2031 | H32: TOTAL
A33: Impuesto de Renta (35% s/ utilidad) | B33: =$B$7*B29 -> 3.6111931e+10 | C33: =$B$7*C29 -> 5.4167896e+09 | D33: =$B$7*D29 -> 9.0279827e+09 | E33: =$B$7*E29 -> 1.0833579e+10 | F33: =$B$7*F29 -> 7.2223862e+09 | G33: =$B$7*G29 -> 3.6111931e+09 | H33: =SUM(C33:G33) -> 3.6111931e+10
A34: Retención en la Fuente (1% s/ ventas) | B34: =$B$8*B16 -> 2258684400 | C34: =$B$8*C16 -> 338802660 | D34: =$B$8*D16 -> 564671100 | E34: =$B$8*E16 -> 677605320 | F34: =$B$8*F16 -> 451736880 | G34: =$B$8*G16 -> 225868440 | H34: =SUM(C34:G34) -> 2258684400
A35: ReteICA (0,33% s/ ventas) | B35: =$B$9*B16 -> 745365852 | C35: =$B$9*C16 -> 1.1180488e+08 | D35: =$B$9*D16 -> 186341463 | E35: =$B$9*E16 -> 2.2360976e+08 | F35: =$B$9*F16 -> 1.4907317e+08 | G35: =$B$9*G16 -> 74536585 | H35: =SUM(C35:G35) -> 745365852
A36: ICA (0,33% s/ ventas) | B36: =$B$10*B16 -> 745365852 | C36: =$B$10*C16 -> 1.1180488e+08 | D36: =$B$10*D16 -> 186341463 | E36: =$B$10*E16 -> 2.2360976e+08 | F36: =$B$10*F16 -> 1.4907317e+08 | G36: =$B$10*G16 -> 74536585 | H36: =SUM(C36:G36) -> 745365852
A37: TOTAL CARGA TRIBUTARIA | B37: =SUM(B33:B36) -> 3.9861347e+10 | C37: =SUM(C33:C36) -> 5.9792021e+09 | D37: =SUM(D33:D36) -> 9.9653368e+09 | E37: =SUM(E33:E36) -> 1.1958404e+10 | F37: =SUM(F33:F36) -> 7.9722694e+09 | G37: =SUM(G33:G36) -> 3.9861347e+09 | H37: =SUM(H33:H36) -> 3.9861347e+10
A39: 6. FLUJO DE CAJA NETO / UTILIDAD NETA (COP)
A40: Concepto | B40: Base 24m (COP) | C40: 2027 | D40: 2028 | E40: 2029 | F40: 2030 | G40: 2031 | H40: TOTAL
A41: Utilidad neta anual (flujo de caja neto) | B41: =B29-B37 -> 6.3315599e+10 | C41: =C29-C37 -> 9.4973398e+09 | D41: =D29-D37 -> 1.58289e+10 | E41: =E29-E37 -> 1.899468e+10 | F41: =F29-F37 -> 1.266312e+10 | G41: =G29-G37 -> 6.3315599e+09 | H41: =SUM(C41:G41) -> 6.3315599e+10
A42: Flujo de caja neto acumulado | B42: — | C42: =C41 -> 9.4973398e+09 | D42: =C42+D41 -> 2.5326239e+10 | E42: =D42+E41 -> 4.4320919e+10 | F42: =E42+F41 -> 5.6984039e+10 | G42: =F42+G41 -> 6.3315599e+10 | H42: =G42 -> 6.3315599e+10
A43: Margen neto (utilidad neta / ventas) | B43: — | C43: =IFERROR(C41/C16,0) -> 0.2803207 | D43: =IFERROR(D41/D16,0) -> 0.2803207 | E43: =IFERROR(E41/E16,0) -> 0.2803207 | F43: =IFERROR(F41/F16,0) -> 0.2803207 | G43: =IFERROR(G41/G16,0) -> 0.2803207 | H43: =IFERROR(H41/H16,0) -> 0.2803207
A44: ROI anual (utilidad neta / costos) | B44: — | C44: =IFERROR(C41/C26,0) -> 0.51605532 | D44: =IFERROR(D41/D26,0) -> 0.51605532 | E44: =IFERROR(E41/E26,0) -> 0.51605532 | F44: =IFERROR(F41/F26,0) -> 0.51605532 | G44: =IFERROR(G41/G26,0) -> 0.51605532 | H44: =IFERROR(H41/H26,0) -> 0.51605532
A46: Nota: las ventas se distribuyen según la curva editable (fila 6). Costos y carga tributaria se prorratean sobre la misma curva, de modo que los totales anuales reconcilian exactamente con el modelo base de 24 meses.

Sheet 2. Santa Bárbara
A1: PROYECTO SANTA BÁRBARA — PROYECCIÓN DE VENTAS 2027–2028
A2: Calle 118 # 22A, Bogotá · 25 apartamentos + 3 terrazas · Cifras en COP · TRM ref. $4.200
A4: 1. SUPUESTOS — DISTRIBUCIÓN DE VENTAS Y TARIFAS IMPOSITIVAS (editables · texto azul)
A5: Concepto | B5: Base 24m (COP) | C5: 2027 | D5: 2028 | E5: TOTAL
A6: Distribución de ventas (% por año) | B6: — | C6: 0.45 | D6: 0.55 | E6: =SUM(C6:D6) -> 1
A7: Impuesto de Renta (s/ utilidad antes de imp.) | B7: 0.35
A8: Retención en la Fuente (s/ ventas) | B8: 0.01
A9: ReteICA (s/ ventas) | B9: 0.0033
A10: ICA (s/ ventas) | B10: 0.0033
A11: 2. INGRESOS POR VENTAS (COP)
A12: Concepto | B12: Base 24m (COP) | C12: 2027 | D12: 2028 | E12: TOTAL
A13: Venta de apartamentos (25 unidades) | B13: 29972175000 | C13: =$B13*C$6 -> 13487478750 | D13: =$B13*D$6 -> 16484696250 | E13: =SUM(C13:D13) -> 29972175000
A14: Venta de terrazas (3 unidades) | B14: 301600500 | C14: =$B14*C$6 -> 135720225 | D14: =$B14*D$6 -> 165880275 | E14: =SUM(C14:D14) -> 301600500
A15: Parqueaderos / depósitos (37 unidades) | B15: 0 | C15: =$B15*C$6 -> 0 | D15: =$B15*D$6 -> 0 | E15: =SUM(C15:D15) -> 0
A16: TOTAL INGRESOS POR VENTAS | B16: =SUM(B13:B15) -> 30273775500 | C16: =SUM(C13:C15) -> 13623198975 | D16: =SUM(D13:D15) -> 16650576525 | E16: =SUM(E13:E15) -> 30273775500
A18: 3. COSTOS DEL PROYECTO (COP)
A19: Concepto | B19: Base 24m (COP) | C19: 2027 | D19: 2028 | E19: TOTAL
A20: CAPEX – Adquisición de terreno | B20: 6779987611 | C20: =$B20*C$6 -> 3.0509944e+09 | D20: =$B20*D$6 -> 3.7289932e+09 | E20: =SUM(C20:D20) -> 6779987611
A21: CAPEX – Construcción directa (obra gris + acabados) | B21: 12280784809 | C21: =$B21*C$6 -> 5.5263532e+09 | D21: =$B21*D$6 -> 6.7544316e+09 | E21: =SUM(C21:D21) -> 12280784809
A22: OPEX – Costos indirectos de construcción | B22: 1843202715 | C22: =$B22*C$6 -> 8.2944122e+08 | D22: =$B22*D$6 -> 1.0137615e+09 | E22: =SUM(C22:D22) -> 1843202715
A23: OPEX – Gastos fiduciarios y administrativos | B23: 1283608081 | C23: =$B23*C$6 -> 5.7762364e+08 | D23: =$B23*D$6 -> 7.0598444e+08 | E23: =SUM(C23:D23) -> 1283608081
A24: OPEX – Costos financieros + 4×1000 GMF | B24: 1075990529 | C24: =$B24*C$6 -> 4.8419574e+08 | D24: =$B24*D$6 -> 5.9179479e+08 | E24: =SUM(C24:D24) -> 1075990529
A25: OPEX – Honorarios, ventas y publicidad | B25: 2724639795 | C25: =$B25*C$6 -> 1.2260879e+09 | D25: =$B25*D$6 -> 1.4985519e+09 | E25: =SUM(C25:D25) -> 2724639795
A26: TOTAL COSTOS DEL PROYECTO | B26: =SUM(B20:B25) -> 25988213540 | C26: =SUM(C20:C25) -> 11694696093 | D26: =SUM(D20:D25) -> 14293517447 | E26: =SUM(E20:E25) -> 25988213540
A28: 4. UTILIDAD ANTES DE IMPUESTOS (COP)
A29: Utilidad antes de impuestos | B29: =B16-B26 -> 4285561960 | C29: =C16-C26 -> 1928502882 | D29: =D16-D26 -> 2357059078 | E29: =SUM(C29:D29) -> 4285561960
A31: 5. CARGA TRIBUTARIA (COP)
A32: Concepto | B32: Base 24m (COP) | C32: 2027 | D32: 2028 | E32: TOTAL
A33: Impuesto de Renta (35% s/ utilidad) | B33: =$B$7*B29 -> 1499946686 | C33: =$B$7*C29 -> 6.7497601e+08 | D33: =$B$7*D29 -> 8.2497068e+08 | E33: =SUM(C33:D33) -> 1499946686
A34: Retención en la Fuente (1% s/ ventas) | B34: =$B$8*B16 -> 302737755 | C34: =$B$8*C16 -> 1.3623199e+08 | D34: =$B$8*D16 -> 1.6650577e+08 | E34: =SUM(C34:D34) -> 302737755
A35: ReteICA (0,33% s/ ventas) | B35: =$B$9*B16 -> 99903459 | C35: =$B$9*C16 -> 44956557 | D35: =$B$9*D16 -> 54946903 | E35: =SUM(C35:D35) -> 99903459
A36: ICA (0,33% s/ ventas) | B36: =$B$10*B16 -> 99903459 | C36: =$B$10*C16 -> 44956557 | D36: =$B$10*D16 -> 54946903 | E36: =SUM(C36:D36) -> 99903459
A37: TOTAL CARGA TRIBUTARIA | B37: =SUM(B33:B36) -> 2.0024914e+09 | C37: =SUM(C33:C36) -> 9.0112111e+08 | D37: =SUM(D33:D36) -> 1.1013702e+09 | E37: =SUM(E33:E36) -> 2.0024914e+09
A39: 6. FLUJO DE CAJA NETO / UTILIDAD NETA (COP)
A40: Concepto | B40: Base 24m (COP) | C40: 2027 | D40: 2028 | E40: TOTAL
A41: Utilidad neta anual (flujo de caja neto) | B41: =B29-B37 -> 2.2830706e+09 | C41: =C29-C37 -> 1.0273818e+09 | D41: =D29-D37 -> 1.2556888e+09 | E41: =SUM(C41:D41) -> 2.2830706e+09
A42: Flujo de caja neto acumulado | B42: — | C42: =C41 -> 1.0273818e+09 | D42: =C42+D41 -> 2.2830706e+09 | E42: =D42 -> 2.2830706e+09
A43: Margen neto (utilidad neta / ventas) | B43: — | C43: =IFERROR(C41/C16,0) -> 0.075414135 | D43: =IFERROR(D41/D16,0) -> 0.075414135 | E43: =IFERROR(E41/E16,0) -> 0.075414135
A44: ROI anual (utilidad neta / costos) | B44: — | C44: =IFERROR(C41/C26,0) -> 0.087850232 | D44: =IFERROR(D41/D26,0) -> 0.087850232 | E44: =IFERROR(E41/E26,0) -> 0.087850232
A46: Nota: proyecto de ciclo corto (24 meses) re-distribuido a 2 años. El GMF 4×1000 está incluido en los costos financieros del proyecto. Totales reconcilian con el modelo base.

Sheet 3. Consolidado
A1: CONSOLIDADO Y UTILIDADES NETAS
A2: Suba Himalaya + Santa Bárbara · Utilidad bruta, carga tributaria y utilidad neta · Cifras en COP · Junio 2026
A4: 1. UTILIDAD NETA CONSOLIDADA (COP)
A5: Concepto | B5: Suba Himalaya | C5: Santa Bárbara | D5: CONSOLIDADO | E5: Nota
A6: Ingresos por ventas | B6: ='1. Suba Himalaya'!H16 -> 225868440000 | C6: ='2. Santa Bárbara'!E16 -> 30273775500 | D6: =B6+C6 -> 256142215500 | E6: Suba: 92 apt+110 parq+18 terr · SB: 25 apt+3 terr
A7: (–) Total costos del proyecto | B7: ='1. Suba Himalaya'!H26 -> 122691494349 | C7: ='2. Santa Bárbara'!E26 -> 25988213540 | D7: =B7+C7 -> 148679707889 | E7: CAPEX + OPEX integrados
A8: UTILIDAD BRUTA ANTES DE IMPUESTOS | B8: =B6-B7 -> 103176945651 | C8: =C6-C7 -> 4285561960 | D8: =D6-D7 -> 107462507611 | E8: Ingresos − costos
A9: (–) Carga tributaria del proyecto | B9: ='1. Suba Himalaya'!H37 -> 3.9861347e+10 | C9: ='2. Santa Bárbara'!E37 -> 2.0024914e+09 | D9: =B9+C9 -> 4.1863838e+10 | E9: Renta + Rte.Fte + ReteICA + ICA de cada proyecto
A10: UTILIDAD NETA DEL PROYECTO | B10: =B8-B9 -> 6.3315599e+10 | C10: =C8-C9 -> 2.2830706e+09 | D10: =D8-D9 -> 6.5598669e+10 | E10: Utilidad neta final por proyecto y consolidada
A11: Margen neto / ventas | B11: =IFERROR(B10/B6,0) -> 0.2803207 | C11: =IFERROR(C10/C6,0) -> 0.075414135 | D11: =IFERROR(D10/D6,0) -> 0.25610253 | E11: Utilidad neta / ingresos
A12: ROI (utilidad neta / costos) | B12: =IFERROR(B10/B7,0) -> 0.51605532 | C12: =IFERROR(C10/C7,0) -> 0.087850232 | D12: =IFERROR(D10/D7,0) -> 0.44120795 | E12: Retorno sobre la inversión total
A14: 2. DESGLOSE DE LA CARGA IMPOSITIVA CONSOLIDADA (Renta · ICA · ReteICA · GMF 4×1000)
A15: Tarifa GMF 4×1000 (4‰ s/ movimientos · editable) | D15: 0.004 | E15: Aplicado sobre desembolsos + recaudos del fideicomiso
A16: Concepto | B16: Suba Himalaya | C16: Santa Bárbara | D16: CONSOLIDADO | E16: Base / observación
A17: Impuesto de Renta (35% s/ utilidad) | B17: ='1. Suba Himalaya'!H33 -> 3.6111931e+10 | C17: ='2. Santa Bárbara'!E33 -> 1499946686 | D17: =B17+C17 -> 3.7611878e+10 | E17: Art. 240 ET · 35% 2026
A18: Retención en la Fuente (1% s/ ventas) | B18: ='1. Suba Himalaya'!H34 -> 2258684400 | C18: ='2. Santa Bárbara'!E34 -> 302737755 | D18: =B18+C18 -> 2561422155 | E18: Art. 401 ET · anticipo descontable
A19: ReteICA (0,33% s/ ventas) | B19: ='1. Suba Himalaya'!H35 -> 745365852 | C19: ='2. Santa Bárbara'!E35 -> 99903459 | D19: =B19+C19 -> 8.4526931e+08 | E19: Acuerdo 65/2002 Bogotá · anticipo
A20: ICA (0,33% s/ ventas) | B20: ='1. Suba Himalaya'!H36 -> 745365852 | C20: ='2. Santa Bárbara'!E36 -> 99903459 | D20: =B20+C20 -> 8.4526931e+08 | E20: Ley 14/1983 · actividad 4010
A21: GMF 4×1000 (s/ movimientos financieros) | B21: — | C21: — | D21: =$D$15*(D6+D7) -> 1.6192877e+09 | E21: Art. 872 ET · 0,4% s/ recaudos + desembolsos
A22: TOTAL CARGA IMPOSITIVA (vista caja tributaria) | B22: =SUM(B17:B20) -> 3.9861347e+10 | C22: =SUM(C17:C20) -> 2.0024914e+09 | D22: =SUM(D17:D21) -> 4.3483126e+10 | E22: Incluye anticipos (Rte.Fte/ReteICA) y GMF
A24: Nota CFO: la Utilidad Neta de la sección 1 se obtiene restando a la utilidad bruta la carga tributaria propia de cada proyecto (Renta + Rte.Fte + ReteICA + ICA). La sección 2 es una vista de caja tributaria ampliada que añade el GMF 4×1000 sobre los movimientos del fideicomiso; las retenciones y el ReteICA son anticipos descontables del impuesto de renta, no costo definitivo adicional.

Sheet 4. Resumen Ejecutivo
A1: MODELO FINANCIERO CONSOLIDADO — RESUMEN EJECUTIVO
A2: Proyecto Suba Himalaya + Proyecto Santa Bárbara · Cifras en COP · TRM ref. $4.200 · Junio 2026
A4: 1. DESCRIPCIÓN DE LOS PROYECTOS
A5: SUBA HIMALAYA: desarrollo residencial en Bogotá de 92 apartamentos, 110 parqueaderos con depósito y 18 terrazas, con un área vendible de 21.919 m². Modelo re-proyectado a 5 años (2027–2031) bajo norma NIF Colombia (NIC 11 / NIIF 15).
A7: SANTA BÁRBARA: proyecto de ciclo corto en la Calle 118 # 22A (Bogotá), 25 apartamentos y 3 terrazas dúplex, área construida de 3.739 m². Modelo re-proyectado a 2 años (2027–2028) con estructura CAPEX/OPEX y crédito constructor.
A10: 2. RESUMEN DE INGRESOS Y RESULTADOS (COP)
A11: Concepto | B11: Suba Himalaya | C11: Santa Bárbara | D11: Consolidado
A12: Ingresos totales proyectados | B12: ='3. Consolidado'!B6 -> 225868440000 | C12: ='3. Consolidado'!C6 -> 30273775500 | D12: ='3. Consolidado'!D6 -> 256142215500
A13: Total costos del proyecto | B13: ='3. Consolidado'!B7 -> 122691494349 | C13: ='3. Consolidado'!C7 -> 25988213540 | D13: ='3. Consolidado'!D7 -> 148679707889
A14: Utilidad bruta antes de impuestos | B14: ='3. Consolidado'!B8 -> 103176945651 | C14: ='3. Consolidado'!C8 -> 4285561960 | D14: ='3. Consolidado'!D8 -> 107462507611
A15: Carga tributaria total | B15: ='3. Consolidado'!B9 -> 3.9861347e+10 | C15: ='3. Consolidado'!C9 -> 2.0024914e+09 | D15: ='3. Consolidado'!D9 -> 4.1863838e+10
A16: UTILIDAD NETA | B16: ='3. Consolidado'!B10 -> 6.3315599e+10 | C16: ='3. Consolidado'!C10 -> 2.2830706e+09 | D16: ='3. Consolidado'!D10 -> 6.5598669e+10
A17: Margen neto / ventas | B17: ='3. Consolidado'!B11 -> 0.2803207 | C17: ='3. Consolidado'!C11 -> 0.075414135 | D17: ='3. Consolidado'!D11 -> 0.25610253
A18: ROI (utilidad neta / costos) | B18: ='3. Consolidado'!B12 -> 0.51605532 | C18: ='3. Consolidado'!C12 -> 0.087850232 | D18: ='3. Consolidado'!D12 -> 0.44120795
A20: 3. IMPACTO DE LA CARGA IMPOSITIVA SOBRE LA RENTABILIDAD
A21: La carga tributaria consolidada (Renta 35%, Retención en la Fuente 1%, ReteICA e ICA 0,33%) asciende a ~COP 41.864 millones, equivalente al 16,3% de los ingresos totales y al 39% de la utilidad bruta. El Impuesto de Renta concentra el grueso de la carga (~COP 37.612 millones). Suba Himalaya soporta prácticamente toda la tributación por su mayor escala y margen, mientras Santa Bárbara —con un margen neto del 7,5%— es mucho más sensible a la carga impositiva y a los costos financieros del crédito constructor. El GMF 4×1000 sobre los movimientos del fideicomiso (~COP 1.619 millones) representa un costo de caja adicional, parcialmente deducible (50%, Art. 115 ET).
A26: 4. CONCLUSIONES SOBRE LA VIABILIDAD FINANCIERA
A27: El portafolio consolidado es financieramente viable: genera ingresos proyectados por ~COP 256.142 millones y una utilidad neta consolidada de ~COP 65.599 millones, con un margen neto del 25,6% y un ROI cercano al 44%. Suba Himalaya es el motor de rentabilidad (margen neto 28,0%, ROI 51,6%) y justifica por sí solo la inversión. Santa Bárbara, aunque con un margen ajustado (7,5%) y mayor exposición a costos financieros, aporta diversificación y liquidez de ciclo corto (2 años) que ayuda a financiar el remanente del fondo. Recomendación: priorizar preventas tempranas en Suba para activar el fideicomiso, vigilar la sensibilidad de Santa Bárbara al costo del crédito (TEA 15,6%) y optimizar la deducibilidad del GMF. El fondo fiduciario de COP 105.000 millones cubre ~71% del costo integrado; el saldo se financia con el recaudo de preventas.
A33: Documento de prefactibilidad · Cifras sujetas a actualización por avance de obra y depuración fiscal · Elaborado con base en el modelo financiero consolidado adjunto.
